{
 "actions": [],
 "allow_rename": 1,
 "creation": "2024-03-14 08:40:00.201139",
 "doctype": "DocType",
 "editable_grid": 1,
 "engine": "InnoDB",
 "field_order": [
  "document_type",
  "sort_order"
 ],
 "fields": [
  {
   "fieldname": "document_type",
   "fieldtype": "Link",
   "in_list_view": 1,
   "label": "Document Type",
   "options": "DocType"
  },
  {
   "fieldname": "sort_order",
   "fieldtype": "Int",
   "in_list_view": 1,
   "label": "Sort Order"
  }
 ],
 "index_web_pages_for_search": 1,
 "istable": 1,
 "links": [],
 "modified": "2024-03-14 08:48:48.738579",
 "modified_by": "Administrator",
 "module": "Configuration",
 "name": "Sync To Client Setting",
 "owner": "Administrator",
 "permissions": [],
 "sort_field": "modified",
 "sort_order": "DESC",
 "states": []
}