{
 "actions": [],
 "allow_rename": 1,
 "creation": "2024-08-13 08:36:23.666851",
 "doctype": "DocType",
 "editable_grid": 1,
 "engine": "InnoDB",
 "field_order": [
  "reference_doctype",
  "reference_name",
  "exchange_rate",
  "column_break_dbae",
  "total_amount",
  "paid_amount",
  "balance"
 ],
 "fields": [
  {
   "fieldname": "reference_doctype",
   "fieldtype": "Link",
   "label": "Reference Doctype",
   "link_filters": "[[{\"fieldname\":\"party_type\",\"field_option\":\"DocType\"},\"name\",\"in\",\"Customer,Vendor,Employee\"]]",
   "options": "DocType"
  },
  {
   "fieldname": "reference_name",
   "fieldtype": "Dynamic Link",
   "label": "Reference Name",
   "options": "reference_doctype"
  },
  {
   "fieldname": "exchange_rate",
   "fieldtype": "Float",
   "label": "Exchange Rate"
  },
  {
   "fieldname": "column_break_dbae",
   "fieldtype": "Column Break"
  },
  {
   "fieldname": "total_amount",
   "fieldtype": "Currency",
   "label": "Total Amount"
  },
  {
   "fieldname": "paid_amount",
   "fieldtype": "Currency",
   "label": "Paid Amount"
  },
  {
   "fieldname": "balance",
   "fieldtype": "Currency",
   "label": "Balance"
  }
 ],
 "index_web_pages_for_search": 1,
 "istable": 1,
 "links": [],
 "modified": "2024-08-13 09:39:13.566168",
 "modified_by": "Administrator",
 "module": "Account",
 "name": "Payment Entry Reference",
 "owner": "Administrator",
 "permissions": [],
 "sort_field": "modified",
 "sort_order": "DESC",
 "states": []
}